<?xml version="1.0" encoding="utf-8"?>
<instrument>
	<colorBackground>130,130,130,255</colorBackground>
	<colorForeground>0,0,0,255</colorForeground>
	<colorGraphBackground>255,255,255,255</colorGraphBackground>
	<colorStatic>0,0,0,255</colorStatic>
	<decimals>1</decimals>
	<divisionFormat>mm:ss</divisionFormat>
	<fontSize>10</fontSize>
	<height>150</height>
	<id>4</id>
	<lineThickness>2</lineThickness>
	<majorCnt>4</majorCnt>
	<markerDt>500</markerDt>
	<markerThickness>1</markerThickness>
	<masterTimeFormat>hh:mm:ss</masterTimeFormat>
	<minorCnt>2</minorCnt>
	<name>Time plot instrument</name>
	<signalId>0</signalId>
	<staticThickness>1</staticThickness>
	<ticksInSecond>100</ticksInSecond>
	<timespan>3000</timespan>
	<type>TIME_PLOT</type>
	<width>300</width>
	<x>0</x>
	<y>0</y>
</instrument>

